quant_sdk/__init__.py
quant_sdk/client.py
quant_sdk-1.0.0.dist-info/LICENSE
quant_sdk-1.0.0.dist-info/METADATA
quant_sdk-1.0.0.dist-info/WHEEL
quant_sdk-1.0.0.dist-info/top_level.txt
quant_sdk-1.0.0.dist-info/RECORD
