Metadata-Version: 2.1
Name: quant-sdk
Version: 1.0.0
Summary: A python wrapper for Blocksize Capitals Core Api
Home-page: https://github.com/Blocksize-Capital-GmbH/QuantSDK.git
Author: Setor Blagogee, Chris Mintern
Author-email: cm@blocksize-capital.com, sb@blocksize-capital.com
License: UNKNOWN
Platform: UNKNOWN
Classifier: Programming Language :: Python :: 3
Classifier: License :: OSI Approved :: GNU General Public License v3 or later (GPLv3+)
Classifier: Operating System :: OS Independent
Requires-Python: >=3.6
